README.rst
setup.py
gevent_openssl/SSL.py
gevent_openssl/__init__.py
gevent_openssl.egg-info/PKG-INFO
gevent_openssl.egg-info/SOURCES.txt
gevent_openssl.egg-info/dependency_links.txt
gevent_openssl.egg-info/not-zip-safe
gevent_openssl.egg-info/pbr.json
gevent_openssl.egg-info/requires.txt
gevent_openssl.egg-info/top_level.txt
gevent_openssl/tests/__init__.py
gevent_openssl/tests/functional.py