Metadata-Version: 1.0
Name: gevent_openssl
Version: 1.2
Summary: A gevent wrapper for pyOpenSSL
Home-page: https://github.com/mjs/gevent_openssl
Author: Menno Finlay-Smits
Author-email: menno@freshfoo.com
License: New BSD
Platform: any
